.gitignore
LICENSE
README.md
customize.py
pyproject.toml
requirements.txt
setup.cfg
setup.py
.github/workflows/CI.template
.github/workflows/CI.yml
.github/workflows/publish.yml
skgpytorch/__init__.py
skgpytorch/_version.py
skgpytorch.egg-info/PKG-INFO
skgpytorch.egg-info/SOURCES.txt
skgpytorch.egg-info/dependency_links.txt
skgpytorch.egg-info/requires.txt
skgpytorch.egg-info/top_level.txt
skgpytorch/metrics/__init__.py
skgpytorch/metrics/metrics.py
skgpytorch/models/__init__.py
skgpytorch/models/base.py
skgpytorch/models/exact_gp.py
skgpytorch/models/sparse_gp.py
skgpytorch/models/sv_gp.py
tests/__init__.py
tests/test_run.py