Metadata-Version: 2.1
Name: skgpytorch
Version: 0.2.0
Summary: example description
Home-page: https://github.com/patel-zeel/skgpytorch
Author: Zeel B Patel
Author-email: patel_zeel@iitgn.ac.in
License: MIT
Platform: UNKNOWN
Requires-Python: >=3.6
License-File: LICENSE
